README.md
setup.cfg
setup.py
cloudgenix_tagger/__init__.py
cloudgenix_tagger.egg-info/PKG-INFO
cloudgenix_tagger.egg-info/SOURCES.txt
cloudgenix_tagger.egg-info/dependency_links.txt
cloudgenix_tagger.egg-info/entry_points.txt
cloudgenix_tagger.egg-info/requires.txt
cloudgenix_tagger.egg-info/top_level.txt