Metadata-Version: 2.1
Name: cloudgenix-tagger
Version: 1.0.1b1
Summary: Utility to manage tags across a large number of CloudGenix sites, elements, interfaces, and Circuit Catagories.
Home-page: https://github.com/ebob9/cloudgenix_tagger
Author: Aaron Edwards
Author-email: cloudgenix_tagger@ebob9.com
License: MIT
Platform: UNKNOWN
Classifier: Development Status :: 4 - Beta
Classifier: Intended Audience :: Developers
Classifier: License :: OSI Approved :: MIT License
Classifier: Programming Language :: Python :: 2.7
Classifier: Programming Language :: Python :: 3
